[["Map",1,2,9,10],"meta::meta",["Map",3,4,5,6,7,8],"astro-version","5.18.1","content-config-digest","9b3c41996c2bb74b","astro-config-digest","{\"root\":{},\"srcDir\":{},\"publicDir\":{},\"outDir\":{},\"cacheDir\":{},\"site\":\"http://localhost:4321\",\"compressHTML\":true,\"base\":\"/\",\"trailingSlash\":\"ignore\",\"output\":\"server\",\"scopedStyleStrategy\":\"attribute\",\"build\":{\"format\":\"directory\",\"client\":{},\"server\":{},\"assets\":\"_astro\",\"serverEntry\":\"entry.mjs\",\"redirects\":false,\"inlineStylesheets\":\"auto\",\"concurrency\":1},\"server\":{\"open\":false,\"host\":false,\"port\":4321,\"streaming\":true,\"allowedHosts\":[]},\"redirects\":{},\"image\":{\"endpoint\":{\"route\":\"/_image\"},\"service\":{\"entrypoint\":\"@astrojs/netlify/image-service.js\",\"config\":{}},\"domains\":[],\"remotePatterns\":[],\"responsiveStyles\":false},\"devToolbar\":{\"enabled\":true},\"markdown\":{\"syntaxHighlight\":{\"type\":\"shiki\",\"excludeLangs\":[\"math\"]},\"shikiConfig\":{\"langs\":[],\"langAlias\":{},\"theme\":\"github-dark\",\"themes\":{},\"wrap\":false,\"transformers\":[]},\"remarkPlugins\":[],\"rehypePlugins\":[],\"remarkRehype\":{},\"gfm\":true,\"smartypants\":true},\"security\":{\"checkOrigin\":true,\"allowedDomains\":[],\"actionBodySizeLimit\":1048576},\"env\":{\"schema\":{},\"validateSecrets\":false},\"experimental\":{\"clientPrerender\":false,\"contentIntellisense\":false,\"headingIdCompat\":false,\"preserveScriptOrder\":false,\"liveContentCollections\":false,\"csp\":false,\"staticImportMetaEnv\":false,\"chromeDevtoolsWorkspace\":false,\"failOnPrerenderConflict\":false,\"svgo\":false},\"legacy\":{\"collections\":false},\"session\":{\"driver\":\"netlify-blobs\",\"options\":{\"name\":\"astro-sessions\",\"consistency\":\"strong\"}}}","blog",["Map",11,12],"number1",{"id":11,"data":13,"body":18,"filePath":19,"assetImports":20,"digest":22,"rendered":23},{"title":14,"description":15,"pubDate":16,"heroImage":17},"Ummm, What.Is.This.Sh!t?","A spectacular intro",["Date","2025-12-01T06:00:00.000Z"],"__ASTRO_IMAGE_","# What is this about\nI gave myself 15 mins to write this first bit. I am a story as old as time so not going too much further there. I need to get some sh!t done and this is a way for me to put that fire to my feet. Put it out into the tiniest little cracked corner of the inner-nets under a decade's worth of piled dust that was always just barely missed when the floor was swept.\n\nYeah, that'll do it. That'll make my productivity skyrocket. Motivate me to do that thing echoing my brain that gets more lost as the cave loses light.\n\nBut seriously, I'm curious, so I ask, what is this sh!t?.\n\nBon Voyage.","src/content/ryan.michael.content/posts/number1.md",[21],"","1e81c28ccbc1c11f",{"html":24,"metadata":25},"\u003Ch1 id=\"what-is-this-about\">What is this about\u003C/h1>\n\u003Cp>I gave myself 15 mins to write this first bit. I am a story as old as time so not going too much further there. I need to get some sh!t done and this is a way for me to put that fire to my feet. Put it out into the tiniest little cracked corner of the inner-nets under a decade’s worth of piled dust that was always just barely missed when the floor was swept.\u003C/p>\n\u003Cp>Yeah, that’ll do it. That’ll make my productivity skyrocket. Motivate me to do that thing echoing my brain that gets more lost as the cave loses light.\u003C/p>\n\u003Cp>But seriously, I’m curious, so I ask, what is this sh!t?.\u003C/p>\n\u003Cp>Bon Voyage.\u003C/p>",{"headings":26,"localImagePaths":31,"remoteImagePaths":32,"frontmatter":33,"imagePaths":38},[27],{"depth":28,"slug":29,"text":30},1,"what-is-this-about","What is this about",[],[],{"title":14,"description":15,"pubDate":34,"heroImage":21,"draft":35,"tags":36},"Dec 01 2025",false,[9,37],"post",[]]